{
 "font": {
   "info": {
     "face":"Unpack",
     "size":"70",
     "bold":"0",
     "italic":"0",
     "chasrset":"",
     "unicode":"0",
     "stretchH":"100",
     "smooth":"1",
     "aa":"1",
     "padding":"0,0,0,0",
     "spacing":"2,2"
    },
   "common": {
     "lineHeight":"75",
     "base":"60",
     "scaleW":"1024",
     "scaleH":"512",
     "pages":"1",
     "packed":"0"
    },
   "pages": {
     "page": {
       "id":"0",
       "file":"unpack70_whitetitle.png"
      }
    },
   "chars": {
     "count":"252",
     "char": [
        {
         "id":"32",
         "x":"613",
         "y":"332",
         "width":"0",
         "height":"0",
         "xoffset":"0",
         "yoffset":"61",
         "xadvance":"11",
         "page":"0",
         "chnl":"0",
         "letter":"space"
        },
        {
         "id":"33",
         "x":"979",
         "y":"130",
         "width":"16",
         "height":"51",
         "xoffset":"3",
         "yoffset":"10",
         "xadvance":"18",
         "page":"0",
         "chnl":"0",
         "letter":"!"
        },
        {
         "id":"34",
         "x":"68",
         "y":"332",
         "width":"21",
         "height":"20",
         "xoffset":"2",
         "yoffset":"11",
         "xadvance":"21",
         "page":"0",
         "chnl":"0",
         "letter":"\""
        },
        {
         "id":"35",
         "x":"43",
         "y":"186",
         "width":"37",
         "height":"50",
         "xoffset":"1",
         "yoffset":"11",
         "xadvance":"37",
         "page":"0",
         "chnl":"0",
         "letter":"#"
        },
        {
         "id":"36",
         "x":"91",
         "y":"130",
         "width":"22",
         "height":"53",
         "xoffset":"1",
         "yoffset":"9",
         "xadvance":"22",
         "page":"0",
         "chnl":"0",
         "letter":"$"
        },
        {
         "id":"37",
         "x":"574",
         "y":"130",
         "width":"27",
         "height":"51",
         "xoffset":"1",
         "yoffset":"11",
         "xadvance":"27",
         "page":"0",
         "chnl":"0",
         "letter":"%"
        },
        {
         "id":"38",
         "x":"82",
         "y":"186",
         "width":"37",
         "height":"50",
         "xoffset":"1",
         "yoffset":"11",
         "xadvance":"37",
         "page":"0",
         "chnl":"0",
         "letter":"&"
        },
        {
         "id":"39",
         "x":"91",
         "y":"332",
         "width":"11",
         "height":"19",
         "xoffset":"2",
         "yoffset":"11",
         "xadvance":"11",
         "page":"0",
         "chnl":"0",
         "letter":"'"
        },
        {
         "id":"40",
         "x":"719",
         "y":"68",
         "width":"13",
         "height":"57",
         "xoffset":"1",
         "yoffset":"8",
         "xadvance":"13",
         "page":"0",
         "chnl":"0",
         "letter":"("
        },
        {
         "id":"41",
         "x":"734",
         "y":"68",
         "width":"13",
         "height":"57",
         "xoffset":"1",
         "yoffset":"8",
         "xadvance":"13",
         "page":"0",
         "chnl":"0",
         "letter":")"
        },
        {
         "id":"42",
         "x":"25",
         "y":"332",
         "width":"20",
         "height":"22",
         "xoffset":"1",
         "yoffset":"12",
         "xadvance":"21",
         "page":"0",
         "chnl":"0",
         "letter":"*"
        },
        {
         "id":"43",
         "x":"2",
         "y":"332",
         "width":"21",
         "height":"22",
         "xoffset":"2",
         "yoffset":"27",
         "xadvance":"22",
         "page":"0",
         "chnl":"0",
         "letter":"+"
        },
        {
         "id":"44",
         "x":"179",
         "y":"332",
         "width":"12",
         "height":"17",
         "xoffset":"1",
         "yoffset":"49",
         "xadvance":"12",
         "page":"0",
         "chnl":"0",
         "letter":","
        },
        {
         "id":"45",
         "x":"381",
         "y":"332",
         "width":"19",
         "height":"13",
         "xoffset":"2",
         "yoffset":"31",
         "xadvance":"20",
         "page":"0",
         "chnl":"0",
         "letter":"-"
        },
        {
         "id":"46",
         "x":"295",
         "y":"332",
         "width":"14",
         "height":"15",
         "xoffset":"2",
         "yoffset":"45",
         "xadvance":"15",
         "page":"0",
         "chnl":"0",
         "letter":"."
        },
        {
         "id":"47",
         "x":"252",
         "y":"186",
         "width":"28",
         "height":"50",
         "xoffset":"1",
         "yoffset":"11",
         "xadvance":"27",
         "page":"0",
         "chnl":"0",
         "letter":"/"
        },
        {
         "id":"48",
         "x":"325",
         "y":"238",
         "width":"24",
         "height":"49",
         "xoffset":"1",
         "yoffset":"12",
         "xadvance":"24",
         "page":"0",
         "chnl":"0",
         "letter":"0"
        },
        {
         "id":"49",
         "x":"122",
         "y":"238",
         "width":"20",
         "height":"50",
         "xoffset":"1",
         "yoffset":"12",
         "xadvance":"20",
         "page":"0",
         "chnl":"0",
         "letter":"1"
        },
        {
         "id":"50",
         "x":"839",
         "y":"186",
         "width":"23",
         "height":"50",
         "xoffset":"1",
         "yoffset":"11",
         "xadvance":"22",
         "page":"0",
         "chnl":"0",
         "letter":"2"
        },
        {
         "id":"51",
         "x":"2",
         "y":"238",
         "width":"22",
         "height":"50",
         "xoffset":"1",
         "yoffset":"11",
         "xadvance":"22",
         "page":"0",
         "chnl":"0",
         "letter":"3"
        },
        {
         "id":"52",
         "x":"481",
         "y":"238",
         "width":"23",
         "height":"49",
         "xoffset":"2",
         "yoffset":"12",
         "xadvance":"24",
         "page":"0",
         "chnl":"0",
         "letter":"4"
        },
        {
         "id":"53",
         "x":"735",
         "y":"186",
         "width":"24",
         "height":"50",
         "xoffset":"2",
         "yoffset":"12",
         "xadvance":"24",
         "page":"0",
         "chnl":"0",
         "letter":"5"
        },
        {
         "id":"54",
         "x":"351",
         "y":"238",
         "width":"24",
         "height":"49",
         "xoffset":"1",
         "yoffset":"12",
         "xadvance":"24",
         "page":"0",
         "chnl":"0",
         "letter":"6"
        },
        {
         "id":"55",
         "x":"606",
         "y":"238",
         "width":"22",
         "height":"49",
         "xoffset":"1",
         "yoffset":"11",
         "xadvance":"21",
         "page":"0",
         "chnl":"0",
         "letter":"7"
        },
        {
         "id":"56",
         "x":"761",
         "y":"186",
         "width":"24",
         "height":"50",
         "xoffset":"1",
         "yoffset":"12",
         "xadvance":"24",
         "page":"0",
         "chnl":"0",
         "letter":"8"
        },
        {
         "id":"57",
         "x":"377",
         "y":"238",
         "width":"24",
         "height":"49",
         "xoffset":"1",
         "yoffset":"12",
         "xadvance":"24",
         "page":"0",
         "chnl":"0",
         "letter":"9"
        },
        {
         "id":"58",
         "x":"552",
         "y":"290",
         "width":"14",
         "height":"33",
         "xoffset":"1",
         "yoffset":"23",
         "xadvance":"14",
         "page":"0",
         "chnl":"0",
         "letter":":"
        },
        {
         "id":"59",
         "x":"537",
         "y":"290",
         "width":"13",
         "height":"34",
         "xoffset":"2",
         "yoffset":"32",
         "xadvance":"13",
         "page":"0",
         "chnl":"0",
         "letter":";"
        },
        {
         "id":"60",
         "x":"633",
         "y":"290",
         "width":"30",
         "height":"28",
         "xoffset":"1",
         "yoffset":"25",
         "xadvance":"31",
         "page":"0",
         "chnl":"0",
         "letter":"<"
        },
        {
         "id":"61",
         "x":"992",
         "y":"290",
         "width":"23",
         "height":"22",
         "xoffset":"2",
         "yoffset":"25",
         "xadvance":"24",
         "page":"0",
         "chnl":"0",
         "letter":"="
        },
        {
         "id":"62",
         "x":"665",
         "y":"290",
         "width":"30",
         "height":"28",
         "xoffset":"1",
         "yoffset":"25",
         "xadvance":"31",
         "page":"0",
         "chnl":"0",
         "letter":">"
        },
        {
         "id":"63",
         "x":"941",
         "y":"68",
         "width":"24",
         "height":"54",
         "xoffset":"3",
         "yoffset":"12",
         "xadvance":"26",
         "page":"0",
         "chnl":"0",
         "letter":"?"
        },
        {
         "id":"64",
         "x":"175",
         "y":"130",
         "width":"42",
         "height":"51",
         "xoffset":"1",
         "yoffset":"12",
         "xadvance":"42",
         "page":"0",
         "chnl":"0",
         "letter":"@"
        },
        {
         "id":"65",
         "x":"631",
         "y":"130",
         "width":"25",
         "height":"51",
         "xoffset":"0",
         "yoffset":"11",
         "xadvance":"24",
         "page":"0",
         "chnl":"0",
         "letter":"A"
        },
        {
         "id":"66",
         "x":"864",
         "y":"186",
         "width":"23",
         "height":"50",
         "xoffset":"1",
         "yoffset":"11",
         "xadvance":"23",
         "page":"0",
         "chnl":"0",
         "letter":"B"
        },
        {
         "id":"67",
         "x":"519",
         "y":"186",
         "width":"25",
         "height":"50",
         "xoffset":"1",
         "yoffset":"12",
         "xadvance":"25",
         "page":"0",
         "chnl":"0",
         "letter":"C"
        },
        {
         "id":"68",
         "x":"837",
         "y":"130",
         "width":"22",
         "height":"51",
         "xoffset":"1",
         "yoffset":"11",
         "xadvance":"22",
         "page":"0",
         "chnl":"0",
         "letter":"D"
        },
        {
         "id":"69",
         "x":"630",
         "y":"238",
         "width":"20",
         "height":"49",
         "xoffset":"1",
         "yoffset":"12",
         "xadvance":"20",
         "page":"0",
         "chnl":"0",
         "letter":"E"
        },
        {
         "id":"70",
         "x":"933",
         "y":"130",
         "width":"21",
         "height":"51",
         "xoffset":"1",
         "yoffset":"11",
         "xadvance":"20",
         "page":"0",
         "chnl":"0",
         "letter":"F"
        },
        {
         "id":"71",
         "x":"546",
         "y":"186",
         "width":"25",
         "height":"50",
         "xoffset":"1",
         "yoffset":"11",
         "xadvance":"25",
         "page":"0",
         "chnl":"0",
         "letter":"G"
        },
        {
         "id":"72",
         "x":"573",
         "y":"186",
         "width":"25",
         "height":"50",
         "xoffset":"1",
         "yoffset":"11",
         "xadvance":"25",
         "page":"0",
         "chnl":"0",
         "letter":"H"
        },
        {
         "id":"73",
         "x":"672",
         "y":"238",
         "width":"12",
         "height":"49",
         "xoffset":"1",
         "yoffset":"11",
         "xadvance":"12",
         "page":"0",
         "chnl":"0",
         "letter":"I"
        },
        {
         "id":"74",
         "x":"685",
         "y":"130",
         "width":"24",
         "height":"51",
         "xoffset":"1",
         "yoffset":"11",
         "xadvance":"24",
         "page":"0",
         "chnl":"0",
         "letter":"J"
        },
        {
         "id":"75",
         "x":"282",
         "y":"186",
         "width":"28",
         "height":"50",
         "xoffset":"1",
         "yoffset":"11",
         "xadvance":"27",
         "page":"0",
         "chnl":"0",
         "letter":"K"
        },
        {
         "id":"76",
         "x":"652",
         "y":"238",
         "width":"18",
         "height":"49",
         "xoffset":"1",
         "yoffset":"12",
         "xadvance":"18",
         "page":"0",
         "chnl":"0",
         "letter":"L"
        },
        {
         "id":"77",
         "x":"219",
         "y":"130",
         "width":"41",
         "height":"51",
         "xoffset":"1",
         "yoffset":"11",
         "xadvance":"40",
         "page":"0",
         "chnl":"0",
         "letter":"M"
        },
        {
         "id":"78",
         "x":"204",
         "y":"238",
         "width":"31",
         "height":"49",
         "xoffset":"1",
         "yoffset":"12",
         "xadvance":"31",
         "page":"0",
         "chnl":"0",
         "letter":"N"
        },
        {
         "id":"79",
         "x":"506",
         "y":"238",
         "width":"23",
         "height":"49",
         "xoffset":"1",
         "yoffset":"11",
         "xadvance":"23",
         "page":"0",
         "chnl":"0",
         "letter":"O"
        },
        {
         "id":"80",
         "x":"26",
         "y":"238",
         "width":"22",
         "height":"50",
         "xoffset":"1",
         "yoffset":"11",
         "xadvance":"22",
         "page":"0",
         "chnl":"0",
         "letter":"P"
        },
        {
         "id":"81",
         "x":"65",
         "y":"130",
         "width":"24",
         "height":"53",
         "xoffset":"1",
         "yoffset":"11",
         "xadvance":"24",
         "page":"0",
         "chnl":"0",
         "letter":"Q"
        },
        {
         "id":"82",
         "x":"889",
         "y":"186",
         "width":"23",
         "height":"50",
         "xoffset":"1",
         "yoffset":"11",
         "xadvance":"23",
         "page":"0",
         "chnl":"0",
         "letter":"R"
        },
        {
         "id":"83",
         "x":"861",
         "y":"130",
         "width":"22",
         "height":"51",
         "xoffset":"1",
         "yoffset":"11",
         "xadvance":"21",
         "page":"0",
         "chnl":"0",
         "letter":"S"
        },
        {
         "id":"84",
         "x":"817",
         "y":"238",
         "width":"22",
         "height":"48",
         "xoffset":"2",
         "yoffset":"13",
         "xadvance":"21",
         "page":"0",
         "chnl":"0",
         "letter":"T"
        },
        {
         "id":"85",
         "x":"711",
         "y":"130",
         "width":"24",
         "height":"51",
         "xoffset":"1",
         "yoffset":"12",
         "xadvance":"24",
         "page":"0",
         "chnl":"0",
         "letter":"U"
        },
        {
         "id":"86",
         "x":"600",
         "y":"186",
         "width":"25",
         "height":"50",
         "xoffset":"1",
         "yoffset":"11",
         "xadvance":"25",
         "page":"0",
         "chnl":"0",
         "letter":"V"
        },
        {
         "id":"87",
         "x":"2",
         "y":"186",
         "width":"39",
         "height":"50",
         "xoffset":"2",
         "yoffset":"11",
         "xadvance":"39",
         "page":"0",
         "chnl":"0",
         "letter":"W"
        },
        {
         "id":"88",
         "x":"432",
         "y":"186",
         "width":"27",
         "height":"50",
         "xoffset":"1",
         "yoffset":"12",
         "xadvance":"26",
         "page":"0",
         "chnl":"0",
         "letter":"X"
        },
        {
         "id":"89",
         "x":"914",
         "y":"186",
         "width":"23",
         "height":"50",
         "xoffset":"1",
         "yoffset":"11",
         "xadvance":"22",
         "page":"0",
         "chnl":"0",
         "letter":"Y"
        },
        {
         "id":"90",
         "x":"50",
         "y":"238",
         "width":"22",
         "height":"50",
         "xoffset":"1",
         "yoffset":"11",
         "xadvance":"22",
         "page":"0",
         "chnl":"0",
         "letter":"Z"
        },
        {
         "id":"91",
         "x":"656",
         "y":"68",
         "width":"19",
         "height":"57",
         "xoffset":"1",
         "yoffset":"9",
         "xadvance":"19",
         "page":"0",
         "chnl":"0",
         "letter":"["
        },
        {
         "id":"92",
         "x":"312",
         "y":"186",
         "width":"28",
         "height":"50",
         "xoffset":"1",
         "yoffset":"11",
         "xadvance":"27",
         "page":"0",
         "chnl":"0",
         "letter":"\\"
        },
        {
         "id":"93",
         "x":"677",
         "y":"68",
         "width":"19",
         "height":"57",
         "xoffset":"1",
         "yoffset":"9",
         "xadvance":"19",
         "page":"0",
         "chnl":"0",
         "letter":"]"
        },
        {
         "id":"94",
         "x":"423",
         "y":"332",
         "width":"15",
         "height":"13",
         "xoffset":"1",
         "yoffset":"13",
         "xadvance":"15",
         "page":"0",
         "chnl":"0",
         "letter":"^"
        },
        {
         "id":"95",
         "x":"471",
         "y":"332",
         "width":"28",
         "height":"11",
         "xoffset":"2",
         "yoffset":"59",
         "xadvance":"29",
         "page":"0",
         "chnl":"0",
         "letter":"_"
        },
        {
         "id":"96",
         "x":"535",
         "y":"332",
         "width":"14",
         "height":"11",
         "xoffset":"2",
         "yoffset":"11",
         "xadvance":"15",
         "page":"0",
         "chnl":"0",
         "letter":"`"
        },
        {
         "id":"97",
         "x":"342",
         "y":"186",
         "width":"28",
         "height":"50",
         "xoffset":"0",
         "yoffset":"12",
         "xadvance":"26",
         "page":"0",
         "chnl":"0",
         "letter":"a"
        },
        {
         "id":"98",
         "x":"737",
         "y":"130",
         "width":"23",
         "height":"51",
         "xoffset":"1",
         "yoffset":"12",
         "xadvance":"23",
         "page":"0",
         "chnl":"0",
         "letter":"b"
        },
        {
         "id":"99",
         "x":"885",
         "y":"130",
         "width":"22",
         "height":"51",
         "xoffset":"1",
         "yoffset":"11",
         "xadvance":"21",
         "page":"0",
         "chnl":"0",
         "letter":"c"
        },
        {
         "id":"100",
         "x":"531",
         "y":"238",
         "width":"23",
         "height":"49",
         "xoffset":"1",
         "yoffset":"12",
         "xadvance":"23",
         "page":"0",
         "chnl":"0",
         "letter":"d"
        },
        {
         "id":"101",
         "x":"144",
         "y":"238",
         "width":"19",
         "height":"50",
         "xoffset":"2",
         "yoffset":"11",
         "xadvance":"20",
         "page":"0",
         "chnl":"0",
         "letter":"e"
        },
        {
         "id":"102",
         "x":"74",
         "y":"238",
         "width":"22",
         "height":"50",
         "xoffset":"1",
         "yoffset":"11",
         "xadvance":"22",
         "page":"0",
         "chnl":"0",
         "letter":"f"
        },
        {
         "id":"103",
         "x":"627",
         "y":"186",
         "width":"25",
         "height":"50",
         "xoffset":"1",
         "yoffset":"12",
         "xadvance":"25",
         "page":"0",
         "chnl":"0",
         "letter":"g"
        },
        {
         "id":"104",
         "x":"658",
         "y":"130",
         "width":"25",
         "height":"51",
         "xoffset":"1",
         "yoffset":"10",
         "xadvance":"25",
         "page":"0",
         "chnl":"0",
         "letter":"h"
        },
        {
         "id":"105",
         "x":"686",
         "y":"238",
         "width":"12",
         "height":"49",
         "xoffset":"2",
         "yoffset":"12",
         "xadvance":"12",
         "page":"0",
         "chnl":"0",
         "letter":"i"
        },
        {
         "id":"106",
         "x":"403",
         "y":"238",
         "width":"24",
         "height":"49",
         "xoffset":"1",
         "yoffset":"12",
         "xadvance":"24",
         "page":"0",
         "chnl":"0",
         "letter":"j"
        },
        {
         "id":"107",
         "x":"237",
         "y":"238",
         "width":"28",
         "height":"49",
         "xoffset":"1",
         "yoffset":"12",
         "xadvance":"28",
         "page":"0",
         "chnl":"0",
         "letter":"k"
        },
        {
         "id":"108",
         "x":"165",
         "y":"238",
         "width":"19",
         "height":"50",
         "xoffset":"1",
         "yoffset":"12",
         "xadvance":"19",
         "page":"0",
         "chnl":"0",
         "letter":"l"
        },
        {
         "id":"109",
         "x":"389",
         "y":"130",
         "width":"38",
         "height":"51",
         "xoffset":"2",
         "yoffset":"10",
         "xadvance":"38",
         "page":"0",
         "chnl":"0",
         "letter":"m"
        },
        {
         "id":"110",
         "x":"461",
         "y":"186",
         "width":"27",
         "height":"50",
         "xoffset":"1",
         "yoffset":"11",
         "xadvance":"26",
         "page":"0",
         "chnl":"0",
         "letter":"n"
        },
        {
         "id":"111",
         "x":"556",
         "y":"238",
         "width":"23",
         "height":"49",
         "xoffset":"1",
         "yoffset":"12",
         "xadvance":"23",
         "page":"0",
         "chnl":"0",
         "letter":"o"
        },
        {
         "id":"112",
         "x":"909",
         "y":"130",
         "width":"22",
         "height":"51",
         "xoffset":"1",
         "yoffset":"10",
         "xadvance":"22",
         "page":"0",
         "chnl":"0",
         "letter":"p"
        },
        {
         "id":"113",
         "x":"762",
         "y":"130",
         "width":"23",
         "height":"51",
         "xoffset":"1",
         "yoffset":"12",
         "xadvance":"23",
         "page":"0",
         "chnl":"0",
         "letter":"q"
        },
        {
         "id":"114",
         "x":"939",
         "y":"186",
         "width":"23",
         "height":"50",
         "xoffset":"1",
         "yoffset":"11",
         "xadvance":"23",
         "page":"0",
         "chnl":"0",
         "letter":"r"
        },
        {
         "id":"115",
         "x":"149",
         "y":"130",
         "width":"24",
         "height":"52",
         "xoffset":"1",
         "yoffset":"10",
         "xadvance":"24",
         "page":"0",
         "chnl":"0",
         "letter":"s"
        },
        {
         "id":"116",
         "x":"429",
         "y":"238",
         "width":"24",
         "height":"49",
         "xoffset":"1",
         "yoffset":"13",
         "xadvance":"22",
         "page":"0",
         "chnl":"0",
         "letter":"t"
        },
        {
         "id":"117",
         "x":"654",
         "y":"186",
         "width":"25",
         "height":"50",
         "xoffset":"2",
         "yoffset":"12",
         "xadvance":"25",
         "page":"0",
         "chnl":"0",
         "letter":"u"
        },
        {
         "id":"118",
         "x":"490",
         "y":"186",
         "width":"27",
         "height":"50",
         "xoffset":"1",
         "yoffset":"12",
         "xadvance":"26",
         "page":"0",
         "chnl":"0",
         "letter":"v"
        },
        {
         "id":"119",
         "x":"429",
         "y":"130",
         "width":"36",
         "height":"51",
         "xoffset":"2",
         "yoffset":"11",
         "xadvance":"36",
         "page":"0",
         "chnl":"0",
         "letter":"w"
        },
        {
         "id":"120",
         "x":"681",
         "y":"186",
         "width":"25",
         "height":"50",
         "xoffset":"1",
         "yoffset":"12",
         "xadvance":"25",
         "page":"0",
         "chnl":"0",
         "letter":"x"
        },
        {
         "id":"121",
         "x":"787",
         "y":"186",
         "width":"24",
         "height":"50",
         "xoffset":"2",
         "yoffset":"12",
         "xadvance":"23",
         "page":"0",
         "chnl":"0",
         "letter":"y"
        },
        {
         "id":"122",
         "x":"964",
         "y":"186",
         "width":"23",
         "height":"50",
         "xoffset":"1",
         "yoffset":"12",
         "xadvance":"23",
         "page":"0",
         "chnl":"0",
         "letter":"z"
        },
        {
         "id":"123",
         "x":"967",
         "y":"68",
         "width":"22",
         "height":"54",
         "xoffset":"1",
         "yoffset":"9",
         "xadvance":"22",
         "page":"0",
         "chnl":"0",
         "letter":"{"
        },
        {
         "id":"124",
         "x":"852",
         "y":"68",
         "width":"12",
         "height":"56",
         "xoffset":"1",
         "yoffset":"8",
         "xadvance":"12",
         "page":"0",
         "chnl":"0",
         "letter":"|"
        },
        {
         "id":"125",
         "x":"991",
         "y":"68",
         "width":"22",
         "height":"54",
         "xoffset":"1",
         "yoffset":"9",
         "xadvance":"22",
         "page":"0",
         "chnl":"0",
         "letter":"}"
        },
        {
         "id":"126",
         "x":"501",
         "y":"332",
         "width":"15",
         "height":"11",
         "xoffset":"2",
         "yoffset":"6",
         "xadvance":"16",
         "page":"0",
         "chnl":"0",
         "letter":"~"
        },
        {
         "id":"161",
         "x":"186",
         "y":"238",
         "width":"16",
         "height":"50",
         "xoffset":"1",
         "yoffset":"11",
         "xadvance":"18",
         "page":"0",
         "chnl":"0",
         "letter":"¡"
        },
        {
         "id":"162",
         "x":"989",
         "y":"186",
         "width":"23",
         "height":"50",
         "xoffset":"1",
         "yoffset":"11",
         "xadvance":"23",
         "page":"0",
         "chnl":"0",
         "letter":"¢"
        },
        {
         "id":"163",
         "x":"267",
         "y":"238",
         "width":"28",
         "height":"49",
         "xoffset":"1",
         "yoffset":"13",
         "xadvance":"28",
         "page":"0",
         "chnl":"0",
         "letter":"£"
        },
        {
         "id":"164",
         "x":"508",
         "y":"290",
         "width":"27",
         "height":"37",
         "xoffset":"1",
         "yoffset":"19",
         "xadvance":"27",
         "page":"0",
         "chnl":"0",
         "letter":"¤"
        },
        {
         "id":"165",
         "x":"787",
         "y":"130",
         "width":"23",
         "height":"51",
         "xoffset":"1",
         "yoffset":"10",
         "xadvance":"22",
         "page":"0",
         "chnl":"0",
         "letter":"¥"
        },
        {
         "id":"166",
         "x":"2",
         "y":"130",
         "width":"12",
         "height":"54",
         "xoffset":"1",
         "yoffset":"10",
         "xadvance":"12",
         "page":"0",
         "chnl":"0",
         "letter":"¦"
        },
        {
         "id":"167",
         "x":"812",
         "y":"130",
         "width":"23",
         "height":"51",
         "xoffset":"1",
         "yoffset":"10",
         "xadvance":"23",
         "page":"0",
         "chnl":"0",
         "letter":"§"
        },
        {
         "id":"168",
         "x":"586",
         "y":"332",
         "width":"13",
         "height":"8",
         "xoffset":"2",
         "yoffset":"9",
         "xadvance":"14",
         "page":"0",
         "chnl":"0",
         "letter":"¨"
        },
        {
         "id":"169",
         "x":"305",
         "y":"130",
         "width":"40",
         "height":"51",
         "xoffset":"1",
         "yoffset":"11",
         "xadvance":"41",
         "page":"0",
         "chnl":"0",
         "letter":"©"
        },
        {
         "id":"170",
         "x":"902",
         "y":"290",
         "width":"16",
         "height":"24",
         "xoffset":"1",
         "yoffset":"12",
         "xadvance":"16",
         "page":"0",
         "chnl":"0",
         "letter":"ª"
        },
        {
         "id":"171",
         "x":"920",
         "y":"290",
         "width":"25",
         "height":"23",
         "xoffset":"2",
         "yoffset":"26",
         "xadvance":"27",
         "page":"0",
         "chnl":"0",
         "letter":"«"
        },
        {
         "id":"172",
         "x":"47",
         "y":"332",
         "width":"19",
         "height":"21",
         "xoffset":"2",
         "yoffset":"30",
         "xadvance":"20",
         "page":"0",
         "chnl":"0",
         "letter":"¬"
        },
        {
         "id":"173",
         "x":"402",
         "y":"332",
         "width":"19",
         "height":"13",
         "xoffset":"2",
         "yoffset":"29",
         "xadvance":"20",
         "page":"0",
         "chnl":"0",
         "letter":"­"
        },
        {
         "id":"174",
         "x":"347",
         "y":"130",
         "width":"40",
         "height":"51",
         "xoffset":"1",
         "yoffset":"11",
         "xadvance":"41",
         "page":"0",
         "chnl":"0",
         "letter":"®"
        },
        {
         "id":"175",
         "x":"567",
         "y":"332",
         "width":"17",
         "height":"9",
         "xoffset":"2",
         "yoffset":"6",
         "xadvance":"18",
         "page":"0",
         "chnl":"0",
         "letter":"¯"
        },
        {
         "id":"176",
         "x":"311",
         "y":"332",
         "width":"12",
         "height":"15",
         "xoffset":"1",
         "yoffset":"11",
         "xadvance":"12",
         "page":"0",
         "chnl":"0",
         "letter":"°"
        },
        {
         "id":"177",
         "x":"568",
         "y":"290",
         "width":"21",
         "height":"32",
         "xoffset":"1",
         "yoffset":"21",
         "xadvance":"21",
         "page":"0",
         "chnl":"0",
         "letter":"±"
        },
        {
         "id":"178",
         "x":"836",
         "y":"290",
         "width":"12",
         "height":"26",
         "xoffset":"1",
         "yoffset":"10",
         "xadvance":"13",
         "page":"0",
         "chnl":"0",
         "letter":"²"
        },
        {
         "id":"179",
         "x":"850",
         "y":"290",
         "width":"12",
         "height":"26",
         "xoffset":"1",
         "yoffset":"12",
         "xadvance":"13",
         "page":"0",
         "chnl":"0",
         "letter":"³"
        },
        {
         "id":"180",
         "x":"551",
         "y":"332",
         "width":"14",
         "height":"11",
         "xoffset":"2",
         "yoffset":"11",
         "xadvance":"15",
         "page":"0",
         "chnl":"0",
         "letter":"´"
        },
        {
         "id":"181",
         "x":"708",
         "y":"186",
         "width":"25",
         "height":"50",
         "xoffset":"1",
         "yoffset":"21",
         "xadvance":"25",
         "page":"0",
         "chnl":"0",
         "letter":"µ"
        },
        {
         "id":"182",
         "x":"539",
         "y":"130",
         "width":"33",
         "height":"51",
         "xoffset":"1",
         "yoffset":"10",
         "xadvance":"34",
         "page":"0",
         "chnl":"0",
         "letter":"¶"
        },
        {
         "id":"183",
         "x":"457",
         "y":"332",
         "width":"12",
         "height":"13",
         "xoffset":"2",
         "yoffset":"32",
         "xadvance":"13",
         "page":"0",
         "chnl":"0",
         "letter":"·"
        },
        {
         "id":"184",
         "x":"235",
         "y":"332",
         "width":"13",
         "height":"16",
         "xoffset":"2",
         "yoffset":"53",
         "xadvance":"14",
         "page":"0",
         "chnl":"0",
         "letter":"¸"
        },
        {
         "id":"185",
         "x":"864",
         "y":"290",
         "width":"11",
         "height":"26",
         "xoffset":"1",
         "yoffset":"12",
         "xadvance":"11",
         "page":"0",
         "chnl":"0",
         "letter":"¹"
        },
        {
         "id":"186",
         "x":"974",
         "y":"290",
         "width":"16",
         "height":"23",
         "xoffset":"1",
         "yoffset":"12",
         "xadvance":"16",
         "page":"0",
         "chnl":"0",
         "letter":"º"
        },
        {
         "id":"187",
         "x":"947",
         "y":"290",
         "width":"25",
         "height":"23",
         "xoffset":"3",
         "yoffset":"26",
         "xadvance":"27",
         "page":"0",
         "chnl":"0",
         "letter":"»"
        },
        {
         "id":"188",
         "x":"190",
         "y":"186",
         "width":"29",
         "height":"50",
         "xoffset":"1",
         "yoffset":"11",
         "xadvance":"30",
         "page":"0",
         "chnl":"0",
         "letter":"¼"
        },
        {
         "id":"189",
         "x":"402",
         "y":"186",
         "width":"28",
         "height":"50",
         "xoffset":"1",
         "yoffset":"11",
         "xadvance":"28",
         "page":"0",
         "chnl":"0",
         "letter":"½"
        },
        {
         "id":"190",
         "x":"221",
         "y":"186",
         "width":"29",
         "height":"50",
         "xoffset":"1",
         "yoffset":"11",
         "xadvance":"30",
         "page":"0",
         "chnl":"0",
         "letter":"¾"
        },
        {
         "id":"191",
         "x":"866",
         "y":"68",
         "width":"26",
         "height":"55",
         "xoffset":"2",
         "yoffset":"8",
         "xadvance":"28",
         "page":"0",
         "chnl":"0",
         "letter":"¿"
        },
        {
         "id":"192",
         "x":"434",
         "y":"2",
         "width":"25",
         "height":"61",
         "xoffset":"0",
         "yoffset":"1",
         "xadvance":"24",
         "page":"0",
         "chnl":"0",
         "letter":"À"
        },
        {
         "id":"193",
         "x":"461",
         "y":"2",
         "width":"25",
         "height":"61",
         "xoffset":"0",
         "yoffset":"1",
         "xadvance":"24",
         "page":"0",
         "chnl":"0",
         "letter":"Á"
        },
        {
         "id":"194",
         "x":"150",
         "y":"2",
         "width":"25",
         "height":"62",
         "xoffset":"0",
         "yoffset":"-0",
         "xadvance":"24",
         "page":"0",
         "chnl":"0",
         "letter":"Â"
        },
        {
         "id":"195",
         "x":"488",
         "y":"2",
         "width":"25",
         "height":"61",
         "xoffset":"0",
         "yoffset":"1",
         "xadvance":"24",
         "page":"0",
         "chnl":"0",
         "letter":"Ã"
        },
        {
         "id":"196",
         "x":"401",
         "y":"68",
         "width":"25",
         "height":"58",
         "xoffset":"0",
         "yoffset":"4",
         "xadvance":"24",
         "page":"0",
         "chnl":"0",
         "letter":"Ä"
        },
        {
         "id":"197",
         "x":"515",
         "y":"2",
         "width":"25",
         "height":"61",
         "xoffset":"0",
         "yoffset":"1",
         "xadvance":"24",
         "page":"0",
         "chnl":"0",
         "letter":"Å"
        },
        {
         "id":"198",
         "x":"467",
         "y":"130",
         "width":"34",
         "height":"51",
         "xoffset":"0",
         "yoffset":"11",
         "xadvance":"33",
         "page":"0",
         "chnl":"0",
         "letter":"Æ"
        },
        {
         "id":"199",
         "x":"428",
         "y":"68",
         "width":"25",
         "height":"58",
         "xoffset":"1",
         "yoffset":"12",
         "xadvance":"25",
         "page":"0",
         "chnl":"0",
         "letter":"Ç"
        },
        {
         "id":"200",
         "x":"303",
         "y":"68",
         "width":"20",
         "height":"59",
         "xoffset":"1",
         "yoffset":"2",
         "xadvance":"20",
         "page":"0",
         "chnl":"0",
         "letter":"È"
        },
        {
         "id":"201",
         "x":"325",
         "y":"68",
         "width":"20",
         "height":"59",
         "xoffset":"1",
         "yoffset":"2",
         "xadvance":"20",
         "page":"0",
         "chnl":"0",
         "letter":"É"
        },
        {
         "id":"202",
         "x":"968",
         "y":"2",
         "width":"20",
         "height":"60",
         "xoffset":"1",
         "yoffset":"1",
         "xadvance":"20",
         "page":"0",
         "chnl":"0",
         "letter":"Ê"
        },
        {
         "id":"203",
         "x":"814",
         "y":"68",
         "width":"20",
         "height":"56",
         "xoffset":"1",
         "yoffset":"5",
         "xadvance":"20",
         "page":"0",
         "chnl":"0",
         "letter":"Ë"
        },
        {
         "id":"204",
         "x":"71",
         "y":"68",
         "width":"14",
         "height":"60",
         "xoffset":"-1",
         "yoffset":"-0",
         "xadvance":"12",
         "page":"0",
         "chnl":"0",
         "letter":"Ì"
        },
        {
         "id":"205",
         "x":"2",
         "y":"68",
         "width":"16",
         "height":"60",
         "xoffset":"1",
         "yoffset":"-0",
         "xadvance":"12",
         "page":"0",
         "chnl":"0",
         "letter":"Í"
        },
        {
         "id":"206",
         "x":"20",
         "y":"68",
         "width":"15",
         "height":"60",
         "xoffset":"0",
         "yoffset":"-0",
         "xadvance":"12",
         "page":"0",
         "chnl":"0",
         "letter":"Î"
        },
        {
         "id":"207",
         "x":"836",
         "y":"68",
         "width":"14",
         "height":"56",
         "xoffset":"1",
         "yoffset":"4",
         "xadvance":"12",
         "page":"0",
         "chnl":"0",
         "letter":"Ï"
        },
        {
         "id":"208",
         "x":"603",
         "y":"130",
         "width":"26",
         "height":"51",
         "xoffset":"1",
         "yoffset":"11",
         "xadvance":"26",
         "page":"0",
         "chnl":"0",
         "letter":"Ð"
        },
        {
         "id":"209",
         "x":"541",
         "y":"68",
         "width":"31",
         "height":"57",
         "xoffset":"1",
         "yoffset":"4",
         "xadvance":"31",
         "page":"0",
         "chnl":"0",
         "letter":"Ñ"
        },
        {
         "id":"210",
         "x":"818",
         "y":"2",
         "width":"23",
         "height":"60",
         "xoffset":"1",
         "yoffset":"-0",
         "xadvance":"23",
         "page":"0",
         "chnl":"0",
         "letter":"Ò"
        },
        {
         "id":"211",
         "x":"843",
         "y":"2",
         "width":"23",
         "height":"60",
         "xoffset":"1",
         "yoffset":"-0",
         "xadvance":"23",
         "page":"0",
         "chnl":"0",
         "letter":"Ó"
        },
        {
         "id":"212",
         "x":"619",
         "y":"2",
         "width":"23",
         "height":"61",
         "xoffset":"1",
         "yoffset":"-1",
         "xadvance":"23",
         "page":"0",
         "chnl":"0",
         "letter":"Ô"
        },
        {
         "id":"213",
         "x":"254",
         "y":"68",
         "width":"23",
         "height":"59",
         "xoffset":"1",
         "yoffset":"1",
         "xadvance":"23",
         "page":"0",
         "chnl":"0",
         "letter":"Õ"
        },
        {
         "id":"214",
         "x":"764",
         "y":"68",
         "width":"23",
         "height":"56",
         "xoffset":"1",
         "yoffset":"4",
         "xadvance":"23",
         "page":"0",
         "chnl":"0",
         "letter":"Ö"
        },
        {
         "id":"215",
         "x":"819",
         "y":"290",
         "width":"15",
         "height":"26",
         "xoffset":"1",
         "yoffset":"24",
         "xadvance":"15",
         "page":"0",
         "chnl":"0",
         "letter":"×"
        },
        {
         "id":"216",
         "x":"581",
         "y":"238",
         "width":"23",
         "height":"49",
         "xoffset":"1",
         "yoffset":"11",
         "xadvance":"23",
         "page":"0",
         "chnl":"0",
         "letter":"Ø"
        },
        {
         "id":"217",
         "x":"542",
         "y":"2",
         "width":"24",
         "height":"61",
         "xoffset":"1",
         "yoffset":"2",
         "xadvance":"24",
         "page":"0",
         "chnl":"0",
         "letter":"Ù"
        },
        {
         "id":"218",
         "x":"792",
         "y":"2",
         "width":"24",
         "height":"60",
         "xoffset":"1",
         "yoffset":"3",
         "xadvance":"24",
         "page":"0",
         "chnl":"0",
         "letter":"Ú"
        },
        {
         "id":"219",
         "x":"230",
         "y":"2",
         "width":"24",
         "height":"62",
         "xoffset":"1",
         "yoffset":"1",
         "xadvance":"24",
         "page":"0",
         "chnl":"0",
         "letter":"Û"
        },
        {
         "id":"220",
         "x":"455",
         "y":"68",
         "width":"24",
         "height":"58",
         "xoffset":"1",
         "yoffset":"5",
         "xadvance":"24",
         "page":"0",
         "chnl":"0",
         "letter":"Ü"
        },
        {
         "id":"221",
         "x":"868",
         "y":"2",
         "width":"23",
         "height":"60",
         "xoffset":"1",
         "yoffset":"1",
         "xadvance":"22",
         "page":"0",
         "chnl":"0",
         "letter":"Ý"
        },
        {
         "id":"222",
         "x":"98",
         "y":"238",
         "width":"22",
         "height":"50",
         "xoffset":"1",
         "yoffset":"11",
         "xadvance":"22",
         "page":"0",
         "chnl":"0",
         "letter":"Þ"
        },
        {
         "id":"223",
         "x":"115",
         "y":"130",
         "width":"32",
         "height":"52",
         "xoffset":"1",
         "yoffset":"11",
         "xadvance":"32",
         "page":"0",
         "chnl":"0",
         "letter":"ß"
        },
        {
         "id":"224",
         "x":"344",
         "y":"2",
         "width":"28",
         "height":"61",
         "xoffset":"0",
         "yoffset":"1",
         "xadvance":"26",
         "page":"0",
         "chnl":"0",
         "letter":"à"
        },
        {
         "id":"225",
         "x":"374",
         "y":"2",
         "width":"28",
         "height":"61",
         "xoffset":"0",
         "yoffset":"1",
         "xadvance":"26",
         "page":"0",
         "chnl":"0",
         "letter":"á"
        },
        {
         "id":"226",
         "x":"120",
         "y":"2",
         "width":"28",
         "height":"62",
         "xoffset":"0",
         "yoffset":"-0",
         "xadvance":"26",
         "page":"0",
         "chnl":"0",
         "letter":"â"
        },
        {
         "id":"227",
         "x":"140",
         "y":"68",
         "width":"28",
         "height":"59",
         "xoffset":"0",
         "yoffset":"3",
         "xadvance":"26",
         "page":"0",
         "chnl":"0",
         "letter":"ã"
        },
        {
         "id":"228",
         "x":"574",
         "y":"68",
         "width":"28",
         "height":"57",
         "xoffset":"0",
         "yoffset":"5",
         "xadvance":"26",
         "page":"0",
         "chnl":"0",
         "letter":"ä"
        },
        {
         "id":"229",
         "x":"404",
         "y":"2",
         "width":"28",
         "height":"61",
         "xoffset":"0",
         "yoffset":"1",
         "xadvance":"26",
         "page":"0",
         "chnl":"0",
         "letter":"å"
        },
        {
         "id":"230",
         "x":"503",
         "y":"130",
         "width":"34",
         "height":"51",
         "xoffset":"1",
         "yoffset":"11",
         "xadvance":"35",
         "page":"0",
         "chnl":"0",
         "letter":"æ"
        },
        {
         "id":"231",
         "x":"279",
         "y":"68",
         "width":"22",
         "height":"59",
         "xoffset":"1",
         "yoffset":"11",
         "xadvance":"21",
         "page":"0",
         "chnl":"0",
         "letter":"ç"
        },
        {
         "id":"232",
         "x":"717",
         "y":"2",
         "width":"19",
         "height":"61",
         "xoffset":"2",
         "yoffset":"-0",
         "xadvance":"20",
         "page":"0",
         "chnl":"0",
         "letter":"è"
        },
        {
         "id":"233",
         "x":"990",
         "y":"2",
         "width":"19",
         "height":"60",
         "xoffset":"2",
         "yoffset":"1",
         "xadvance":"20",
         "page":"0",
         "chnl":"0",
         "letter":"é"
        },
        {
         "id":"234",
         "x":"306",
         "y":"2",
         "width":"19",
         "height":"62",
         "xoffset":"2",
         "yoffset":"-1",
         "xadvance":"20",
         "page":"0",
         "chnl":"0",
         "letter":"ê"
        },
        {
         "id":"235",
         "x":"698",
         "y":"68",
         "width":"19",
         "height":"57",
         "xoffset":"2",
         "yoffset":"4",
         "xadvance":"20",
         "page":"0",
         "chnl":"0",
         "letter":"ë"
        },
        {
         "id":"236",
         "x":"37",
         "y":"68",
         "width":"15",
         "height":"60",
         "xoffset":"-2",
         "yoffset":"1",
         "xadvance":"12",
         "page":"0",
         "chnl":"0",
         "letter":"ì"
        },
        {
         "id":"237",
         "x":"54",
         "y":"68",
         "width":"15",
         "height":"60",
         "xoffset":"2",
         "yoffset":"1",
         "xadvance":"12",
         "page":"0",
         "chnl":"0",
         "letter":"í"
        },
        {
         "id":"238",
         "x":"327",
         "y":"2",
         "width":"15",
         "height":"62",
         "xoffset":"-0",
         "yoffset":"-1",
         "xadvance":"12",
         "page":"0",
         "chnl":"0",
         "letter":"î"
        },
        {
         "id":"239",
         "x":"749",
         "y":"68",
         "width":"13",
         "height":"57",
         "xoffset":"1",
         "yoffset":"4",
         "xadvance":"12",
         "page":"0",
         "chnl":"0",
         "letter":"ï"
        },
        {
         "id":"240",
         "x":"297",
         "y":"238",
         "width":"26",
         "height":"49",
         "xoffset":"1",
         "yoffset":"12",
         "xadvance":"26",
         "page":"0",
         "chnl":"0",
         "letter":"ð"
        },
        {
         "id":"241",
         "x":"170",
         "y":"68",
         "width":"27",
         "height":"59",
         "xoffset":"1",
         "yoffset":"2",
         "xadvance":"26",
         "page":"0",
         "chnl":"0",
         "letter":"ñ"
        },
        {
         "id":"242",
         "x":"893",
         "y":"2",
         "width":"23",
         "height":"60",
         "xoffset":"1",
         "yoffset":"1",
         "xadvance":"23",
         "page":"0",
         "chnl":"0",
         "letter":"ò"
        },
        {
         "id":"243",
         "x":"918",
         "y":"2",
         "width":"23",
         "height":"60",
         "xoffset":"1",
         "yoffset":"1",
         "xadvance":"23",
         "page":"0",
         "chnl":"0",
         "letter":"ó"
        },
        {
         "id":"244",
         "x":"644",
         "y":"2",
         "width":"23",
         "height":"61",
         "xoffset":"1",
         "yoffset":"-0",
         "xadvance":"23",
         "page":"0",
         "chnl":"0",
         "letter":"ô"
        },
        {
         "id":"245",
         "x":"481",
         "y":"68",
         "width":"23",
         "height":"58",
         "xoffset":"1",
         "yoffset":"3",
         "xadvance":"23",
         "page":"0",
         "chnl":"0",
         "letter":"õ"
        },
        {
         "id":"246",
         "x":"789",
         "y":"68",
         "width":"23",
         "height":"56",
         "xoffset":"1",
         "yoffset":"5",
         "xadvance":"23",
         "page":"0",
         "chnl":"0",
         "letter":"ö"
        },
        {
         "id":"247",
         "x":"795",
         "y":"290",
         "width":"22",
         "height":"26",
         "xoffset":"1",
         "yoffset":"26",
         "xadvance":"23",
         "page":"0",
         "chnl":"0",
         "letter":"÷"
        },
        {
         "id":"248",
         "x":"455",
         "y":"238",
         "width":"24",
         "height":"49",
         "xoffset":"0",
         "yoffset":"12",
         "xadvance":"24",
         "page":"0",
         "chnl":"0",
         "letter":"ø"
        },
        {
         "id":"249",
         "x":"738",
         "y":"2",
         "width":"25",
         "height":"60",
         "xoffset":"2",
         "yoffset":"2",
         "xadvance":"25",
         "page":"0",
         "chnl":"0",
         "letter":"ù"
        },
        {
         "id":"250",
         "x":"765",
         "y":"2",
         "width":"25",
         "height":"60",
         "xoffset":"2",
         "yoffset":"2",
         "xadvance":"25",
         "page":"0",
         "chnl":"0",
         "letter":"ú"
        },
        {
         "id":"251",
         "x":"177",
         "y":"2",
         "width":"25",
         "height":"62",
         "xoffset":"2",
         "yoffset":"-0",
         "xadvance":"25",
         "page":"0",
         "chnl":"0",
         "letter":"û"
        },
        {
         "id":"252",
         "x":"604",
         "y":"68",
         "width":"25",
         "height":"57",
         "xoffset":"2",
         "yoffset":"5",
         "xadvance":"25",
         "page":"0",
         "chnl":"0",
         "letter":"ü"
        },
        {
         "id":"253",
         "x":"228",
         "y":"68",
         "width":"24",
         "height":"59",
         "xoffset":"2",
         "yoffset":"3",
         "xadvance":"23",
         "page":"0",
         "chnl":"0",
         "letter":"ý"
        },
        {
         "id":"254",
         "x":"956",
         "y":"130",
         "width":"21",
         "height":"51",
         "xoffset":"1",
         "yoffset":"10",
         "xadvance":"21",
         "page":"0",
         "chnl":"0",
         "letter":"þ"
        },
        {
         "id":"261",
         "x":"368",
         "y":"68",
         "width":"31",
         "height":"58",
         "xoffset":"0",
         "yoffset":"11",
         "xadvance":"26",
         "page":"0",
         "chnl":"0",
         "letter":"ą"
        },
        {
         "id":"263",
         "x":"693",
         "y":"2",
         "width":"22",
         "height":"61",
         "xoffset":"1",
         "yoffset":"1",
         "xadvance":"21",
         "page":"0",
         "chnl":"0",
         "letter":"ć"
        },
        {
         "id":"281",
         "x":"347",
         "y":"68",
         "width":"19",
         "height":"59",
         "xoffset":"2",
         "yoffset":"11",
         "xadvance":"20",
         "page":"0",
         "chnl":"0",
         "letter":"ę"
        },
        {
         "id":"287",
         "x":"93",
         "y":"2",
         "width":"25",
         "height":"63",
         "xoffset":"1",
         "yoffset":"-1",
         "xadvance":"25",
         "page":"0",
         "chnl":"0",
         "letter":"ğ"
        },
        {
         "id":"304",
         "x":"87",
         "y":"68",
         "width":"12",
         "height":"60",
         "xoffset":"1",
         "yoffset":"-0",
         "xadvance":"12",
         "page":"0",
         "chnl":"0",
         "letter":"İ"
        },
        {
         "id":"305",
         "x":"700",
         "y":"238",
         "width":"12",
         "height":"49",
         "xoffset":"2",
         "yoffset":"12",
         "xadvance":"12",
         "page":"0",
         "chnl":"0",
         "letter":"ı"
        },
        {
         "id":"322",
         "x":"813",
         "y":"186",
         "width":"24",
         "height":"50",
         "xoffset":"1",
         "yoffset":"12",
         "xadvance":"24",
         "page":"0",
         "chnl":"0",
         "letter":"ł"
        },
        {
         "id":"324",
         "x":"199",
         "y":"68",
         "width":"27",
         "height":"59",
         "xoffset":"1",
         "yoffset":"2",
         "xadvance":"26",
         "page":"0",
         "chnl":"0",
         "letter":"ń"
        },
        {
         "id":"338",
         "x":"121",
         "y":"186",
         "width":"33",
         "height":"50",
         "xoffset":"1",
         "yoffset":"11",
         "xadvance":"33",
         "page":"0",
         "chnl":"0",
         "letter":"Œ"
        },
        {
         "id":"339",
         "x":"156",
         "y":"186",
         "width":"32",
         "height":"50",
         "xoffset":"1",
         "yoffset":"11",
         "xadvance":"32",
         "page":"0",
         "chnl":"0",
         "letter":"œ"
        },
        {
         "id":"347",
         "x":"256",
         "y":"2",
         "width":"24",
         "height":"62",
         "xoffset":"1",
         "yoffset":"-0",
         "xadvance":"24",
         "page":"0",
         "chnl":"0",
         "letter":"ś"
        },
        {
         "id":"351",
         "x":"568",
         "y":"2",
         "width":"24",
         "height":"61",
         "xoffset":"1",
         "yoffset":"10",
         "xadvance":"24",
         "page":"0",
         "chnl":"0",
         "letter":"ş"
        },
        {
         "id":"352",
         "x":"282",
         "y":"2",
         "width":"22",
         "height":"62",
         "xoffset":"1",
         "yoffset":"-0",
         "xadvance":"21",
         "page":"0",
         "chnl":"0",
         "letter":"Š"
        },
        {
         "id":"353",
         "x":"204",
         "y":"2",
         "width":"24",
         "height":"62",
         "xoffset":"1",
         "yoffset":"-0",
         "xadvance":"24",
         "page":"0",
         "chnl":"0",
         "letter":"š"
        },
        {
         "id":"376",
         "x":"631",
         "y":"68",
         "width":"23",
         "height":"57",
         "xoffset":"1",
         "yoffset":"4",
         "xadvance":"22",
         "page":"0",
         "chnl":"0",
         "letter":"Ÿ"
        },
        {
         "id":"378",
         "x":"943",
         "y":"2",
         "width":"23",
         "height":"60",
         "xoffset":"1",
         "yoffset":"2",
         "xadvance":"23",
         "page":"0",
         "chnl":"0",
         "letter":"ź"
        },
        {
         "id":"381",
         "x":"669",
         "y":"2",
         "width":"22",
         "height":"61",
         "xoffset":"1",
         "yoffset":"-0",
         "xadvance":"22",
         "page":"0",
         "chnl":"0",
         "letter":"Ž"
        },
        {
         "id":"382",
         "x":"594",
         "y":"2",
         "width":"23",
         "height":"61",
         "xoffset":"1",
         "yoffset":"1",
         "xadvance":"23",
         "page":"0",
         "chnl":"0",
         "letter":"ž"
        },
        {
         "id":"402",
         "x":"2",
         "y":"2",
         "width":"36",
         "height":"64",
         "xoffset":"8",
         "yoffset":"7",
         "xadvance":"44",
         "page":"0",
         "chnl":"0",
         "letter":"ƒ"
        },
        {
         "id":"710",
         "x":"440",
         "y":"332",
         "width":"15",
         "height":"13",
         "xoffset":"1",
         "yoffset":"13",
         "xadvance":"15",
         "page":"0",
         "chnl":"0",
         "letter":"ˆ"
        },
        {
         "id":"732",
         "x":"518",
         "y":"332",
         "width":"15",
         "height":"11",
         "xoffset":"2",
         "yoffset":"12",
         "xadvance":"17",
         "page":"0",
         "chnl":"0",
         "letter":"˜"
        },
        {
         "id":"1044",
         "x":"40",
         "y":"2",
         "width":"51",
         "height":"63",
         "xoffset":"3",
         "yoffset":"8",
         "xadvance":"53",
         "page":"0",
         "chnl":"0",
         "letter":"Д"
        },
        {
         "id":"1059",
         "x":"894",
         "y":"68",
         "width":"45",
         "height":"54",
         "xoffset":"3",
         "yoffset":"8",
         "xadvance":"45",
         "page":"0",
         "chnl":"0",
         "letter":"У"
        },
        {
         "id":"1060",
         "x":"16",
         "y":"130",
         "width":"47",
         "height":"53",
         "xoffset":"2",
         "yoffset":"8",
         "xadvance":"49",
         "page":"0",
         "chnl":"0",
         "letter":"Ф"
        },
        {
         "id":"1073",
         "x":"101",
         "y":"68",
         "width":"37",
         "height":"59",
         "xoffset":"4",
         "yoffset":"3",
         "xadvance":"42",
         "page":"0",
         "chnl":"0",
         "letter":"б"
        },
        {
         "id":"1074",
         "x":"447",
         "y":"290",
         "width":"29",
         "height":"40",
         "xoffset":"7",
         "yoffset":"21",
         "xadvance":"37",
         "page":"0",
         "chnl":"0",
         "letter":"в"
        },
        {
         "id":"1075",
         "x":"351",
         "y":"290",
         "width":"30",
         "height":"40",
         "xoffset":"7",
         "yoffset":"21",
         "xadvance":"35",
         "page":"0",
         "chnl":"0",
         "letter":"г"
        },
        {
         "id":"1076",
         "x":"771",
         "y":"238",
         "width":"44",
         "height":"48",
         "xoffset":"3",
         "yoffset":"21",
         "xadvance":"47",
         "page":"0",
         "chnl":"0",
         "letter":"д"
        },
        {
         "id":"1078",
         "x":"956",
         "y":"238",
         "width":"50",
         "height":"40",
         "xoffset":"2",
         "yoffset":"21",
         "xadvance":"51",
         "page":"0",
         "chnl":"0",
         "letter":"ж"
        },
        {
         "id":"1079",
         "x":"925",
         "y":"238",
         "width":"29",
         "height":"41",
         "xoffset":"3",
         "yoffset":"21",
         "xadvance":"34",
         "page":"0",
         "chnl":"0",
         "letter":"з"
        },
        {
         "id":"1080",
         "x":"211",
         "y":"290",
         "width":"33",
         "height":"40",
         "xoffset":"7",
         "yoffset":"21",
         "xadvance":"44",
         "page":"0",
         "chnl":"0",
         "letter":"и"
        },
        {
         "id":"1081",
         "x":"506",
         "y":"68",
         "width":"33",
         "height":"57",
         "xoffset":"7",
         "yoffset":"4",
         "xadvance":"44",
         "page":"0",
         "chnl":"0",
         "letter":"й"
        },
        {
         "id":"1082",
         "x":"316",
         "y":"290",
         "width":"33",
         "height":"40",
         "xoffset":"7",
         "yoffset":"21",
         "xadvance":"39",
         "page":"0",
         "chnl":"0",
         "letter":"к"
        },
        {
         "id":"1083",
         "x":"136",
         "y":"290",
         "width":"36",
         "height":"40",
         "xoffset":"1",
         "yoffset":"21",
         "xadvance":"41",
         "page":"0",
         "chnl":"0",
         "letter":"л"
        },
        {
         "id":"1084",
         "x":"52",
         "y":"290",
         "width":"40",
         "height":"40",
         "xoffset":"7",
         "yoffset":"21",
         "xadvance":"51",
         "page":"0",
         "chnl":"0",
         "letter":"м"
        },
        {
         "id":"1085",
         "x":"246",
         "y":"290",
         "width":"33",
         "height":"40",
         "xoffset":"7",
         "yoffset":"21",
         "xadvance":"44",
         "page":"0",
         "chnl":"0",
         "letter":"н"
        },
        {
         "id":"1087",
         "x":"281",
         "y":"290",
         "width":"33",
         "height":"40",
         "xoffset":"7",
         "yoffset":"21",
         "xadvance":"44",
         "page":"0",
         "chnl":"0",
         "letter":"п"
        },
        {
         "id":"1089",
         "x":"892",
         "y":"238",
         "width":"31",
         "height":"41",
         "xoffset":"4",
         "yoffset":"21",
         "xadvance":"36",
         "page":"0",
         "chnl":"0",
         "letter":"с"
        },
        {
         "id":"1090",
         "x":"174",
         "y":"290",
         "width":"35",
         "height":"40",
         "xoffset":"1",
         "yoffset":"21",
         "xadvance":"35",
         "page":"0",
         "chnl":"0",
         "letter":"т"
        },
        {
         "id":"1095",
         "x":"415",
         "y":"290",
         "width":"30",
         "height":"40",
         "xoffset":"3",
         "yoffset":"21",
         "xadvance":"37",
         "page":"0",
         "chnl":"0",
         "letter":"ч"
        },
        {
         "id":"1096",
         "x":"2",
         "y":"290",
         "width":"48",
         "height":"40",
         "xoffset":"7",
         "yoffset":"21",
         "xadvance":"59",
         "page":"0",
         "chnl":"0",
         "letter":"ш"
        },
        {
         "id":"1097",
         "x":"714",
         "y":"238",
         "width":"55",
         "height":"48",
         "xoffset":"7",
         "yoffset":"21",
         "xadvance":"61",
         "page":"0",
         "chnl":"0",
         "letter":"щ"
        },
        {
         "id":"1099",
         "x":"94",
         "y":"290",
         "width":"40",
         "height":"40",
         "xoffset":"7",
         "yoffset":"21",
         "xadvance":"51",
         "page":"0",
         "chnl":"0",
         "letter":"ы"
        },
        {
         "id":"1100",
         "x":"478",
         "y":"290",
         "width":"28",
         "height":"40",
         "xoffset":"7",
         "yoffset":"21",
         "xadvance":"35",
         "page":"0",
         "chnl":"0",
         "letter":"ь"
        },
        {
         "id":"1102",
         "x":"841",
         "y":"238",
         "width":"49",
         "height":"41",
         "xoffset":"7",
         "yoffset":"21",
         "xadvance":"57",
         "page":"0",
         "chnl":"0",
         "letter":"ю"
        },
        {
         "id":"1103",
         "x":"383",
         "y":"290",
         "width":"30",
         "height":"40",
         "xoffset":"2",
         "yoffset":"21",
         "xadvance":"37",
         "page":"0",
         "chnl":"0",
         "letter":"я"
        },
        {
         "id":"8211",
         "x":"357",
         "y":"332",
         "width":"22",
         "height":"13",
         "xoffset":"2",
         "yoffset":"32",
         "xadvance":"23",
         "page":"0",
         "chnl":"0",
         "letter":"–"
        },
        {
         "id":"8212",
         "x":"325",
         "y":"332",
         "width":"30",
         "height":"13",
         "xoffset":"2",
         "yoffset":"33",
         "xadvance":"30",
         "page":"0",
         "chnl":"0",
         "letter":"—"
        },
        {
         "id":"8216",
         "x":"207",
         "y":"332",
         "width":"12",
         "height":"17",
         "xoffset":"2",
         "yoffset":"11",
         "xadvance":"12",
         "page":"0",
         "chnl":"0",
         "letter":"‘"
        },
        {
         "id":"8217",
         "x":"221",
         "y":"332",
         "width":"12",
         "height":"17",
         "xoffset":"1",
         "yoffset":"11",
         "xadvance":"12",
         "page":"0",
         "chnl":"0",
         "letter":"’"
        },
        {
         "id":"8218",
         "x":"193",
         "y":"332",
         "width":"12",
         "height":"17",
         "xoffset":"2",
         "yoffset":"44",
         "xadvance":"13",
         "page":"0",
         "chnl":"0",
         "letter":"‚"
        },
        {
         "id":"8220",
         "x":"129",
         "y":"332",
         "width":"23",
         "height":"17",
         "xoffset":"2",
         "yoffset":"12",
         "xadvance":"24",
         "page":"0",
         "chnl":"0",
         "letter":"“"
        },
        {
         "id":"8221",
         "x":"154",
         "y":"332",
         "width":"23",
         "height":"17",
         "xoffset":"1",
         "yoffset":"12",
         "xadvance":"24",
         "page":"0",
         "chnl":"0",
         "letter":"”"
        },
        {
         "id":"8222",
         "x":"104",
         "y":"332",
         "width":"23",
         "height":"17",
         "xoffset":"2",
         "yoffset":"44",
         "xadvance":"24",
         "page":"0",
         "chnl":"0",
         "letter":"„"
        },
        {
         "id":"8224",
         "x":"591",
         "y":"290",
         "width":"19",
         "height":"30",
         "xoffset":"1",
         "yoffset":"11",
         "xadvance":"20",
         "page":"0",
         "chnl":"0",
         "letter":"†"
        },
        {
         "id":"8225",
         "x":"612",
         "y":"290",
         "width":"19",
         "height":"30",
         "xoffset":"1",
         "yoffset":"11",
         "xadvance":"20",
         "page":"0",
         "chnl":"0",
         "letter":"‡"
        },
        {
         "id":"8226",
         "x":"877",
         "y":"290",
         "width":"23",
         "height":"25",
         "xoffset":"2",
         "yoffset":"25",
         "xadvance":"24",
         "page":"0",
         "chnl":"0",
         "letter":"•"
        },
        {
         "id":"8230",
         "x":"250",
         "y":"332",
         "width":"43",
         "height":"15",
         "xoffset":"2",
         "yoffset":"46",
         "xadvance":"44",
         "page":"0",
         "chnl":"0",
         "letter":"…"
        },
        {
         "id":"8240",
         "x":"262",
         "y":"130",
         "width":"41",
         "height":"51",
         "xoffset":"0",
         "yoffset":"11",
         "xadvance":"41",
         "page":"0",
         "chnl":"0",
         "letter":"‰"
        },
        {
         "id":"8249",
         "x":"697",
         "y":"290",
         "width":"30",
         "height":"28",
         "xoffset":"1",
         "yoffset":"25",
         "xadvance":"31",
         "page":"0",
         "chnl":"0",
         "letter":"‹"
        },
        {
         "id":"8250",
         "x":"729",
         "y":"290",
         "width":"30",
         "height":"28",
         "xoffset":"1",
         "yoffset":"25",
         "xadvance":"31",
         "page":"0",
         "chnl":"0",
         "letter":"›"
        },
        {
         "id":"8364",
         "x":"372",
         "y":"186",
         "width":"28",
         "height":"50",
         "xoffset":"1",
         "yoffset":"12",
         "xadvance":"28",
         "page":"0",
         "chnl":"0",
         "letter":"€"
        },
        {
         "id":"8482",
         "x":"761",
         "y":"290",
         "width":"32",
         "height":"27",
         "xoffset":"1",
         "yoffset":"11",
         "xadvance":"33",
         "page":"0",
         "chnl":"0",
         "letter":"™"
        }
      ]
    }
  }
}